codesnipper-0.1.18.21.dist-info/licenses/LICENSE
snipper/__init__.py
snipper/block_parsing.py
snipper/fix_bf.py
snipper/fix_cite.py
snipper/fix_i.py
snipper/fix_o.py
snipper/fix_r.py
snipper/fix_s.py
snipper/legacy.py
snipper/load_citations.py
snipper/snip_dir.py
snipper/snipper_main.py
snipper/test.py
snipper/version.py
codesnipper-0.1.18.21.dist-info/METADATA
codesnipper-0.1.18.21.dist-info/WHEEL
codesnipper-0.1.18.21.dist-info/top_level.txt
codesnipper-0.1.18.21.dist-info/RECORD
